opol/__init__.py
opol/main.py
opol/api/__init__.py
opol/api/articles.py
opol/api/classification.py
opol/api/client_base.py
opol/api/entities.py
opol/api/geojson.py
opol-0.1.9.dist-info/LICENSE
opol-0.1.9.dist-info/METADATA
opol-0.1.9.dist-info/WHEEL
opol-0.1.9.dist-info/top_level.txt
opol-0.1.9.dist-info/RECORD
