Metadata-Version: 2.1
Name: opol
Version: 0.1.9
Summary: Main API client to interact with all OPOL services.
Home-page: https://github.com/open-politics/opol
Author: Jim Vincent Wagner
Author-email: Jim Vincent Wagner <jimvw@open-politics.org>
License: MIT
Project-URL: Bug Tracker, https://github.com/open-politics/opol/issues
Classifier: Programming Language :: Python :: 3
Classifier: License :: OSI Approved :: MIT License
Classifier: Operating System :: OS Independent
Requires-Python: >=3.10
License-File: LICENSE
Requires-Dist: requests
Requires-Dist: pydantic
